fxtensor_salmon/__init__.py
fxtensor_salmon-0.2.2.dist-info/licenses/LICENSE
fxtensor_salmon-0.2.2.dist-info/METADATA
fxtensor_salmon-0.2.2.dist-info/WHEEL
fxtensor_salmon-0.2.2.dist-info/top_level.txt
fxtensor_salmon-0.2.2.dist-info/RECORD
