Metadata-Version: 2.4
Name: fxtensor_salmon
Version: 0.2.2
Summary: Markov Tensor Module
Author-email: Tadachika Oki <sakesnare@gmail.com>
License: Copyright 2025 Tadachika Oki
Project-URL: Homepage, https://github.com/salmonsnare/fxtensor-salmon
Classifier: Programming Language :: Python :: 3
Classifier: License :: OSI Approved :: MIT License
Classifier: Operating System :: OS Independent
Classifier: Topic :: Scientific/Engineering :: Mathematics
Requires-Python: >=3.8
License-File: LICENSE
Requires-Dist: numpy>=1.20.0
Dynamic: license-file
